{
  "_meta": {
    "count": 4
  },
  "events": [
    {
      "wordpressId": 4096,
      "status": "publish",
      "title": "2026 Joe Rossi Umpires Hall of Fame Presents - The Umpire's Cup IV",
      "slug": "2026-hof-golf-tournament",
      "url": "https://jrhof.org/2026-hof-golf-tournament/",
      "eventType": "golf-tournament",
      "year": 2026,
      "publishedAt": "2026-03-21 16:24:18",
      "modifiedAt": "2026-03-23 02:05:24",
      "categories": [
        {
          "domain": "category",
          "nicename": "golf",
          "label": "Golf"
        }
      ],
      "contentText": "2026 Joe Rossi Umpires Hall of Fame Presents - The Umpire's Cup IV Days Hours Minutes Seconds Check back soon for photos of this special event. The Joe Rossi Umpires Hall of Fame Golf Tournament is a long‑standing tradition bringing golfers together for a fun, relaxed day of golf in support of the Joe Rossi Umpires Hall of Fame. This event celebrates community, camaraderie, and the lasting legacy of all who have contributed so much to the game of baseball in Colorado. Register Now Event Details 📅 Date: Saturday, June 27, 2026 ⏰ Time: 8:00 a.m. 💲 Entry Fee: $130 per golfer 📍 Location: Applewood Golf Club 14001 W. 32nd Ave. Golden, CO 80401 Registration Register Now Raffle Tickets & Mulligans Make your day on the course even more fun while supporting the Joe Rossi Umpires Hall of Fame. Save time in line during check in and purchase your raffle tickets and mulligans in advance! Click to Purchase Click to Purchase Can't Make It... Donate Instead! If you’re unable to attend the tournament, you can still support the Joe Rossi Umpires Hall of Fame. Choose a one-time donation or become a monthly supporter to help preserve the legacy of baseball officiating in Colorado. Support The Hall of Fame Share Blocksy: Share Box",
      "wordCount": 209,
      "links": [
        "https://www.eventbrite.com/e/joe-rossi-hof-golf-tournament-2026-tickets-1985644019715",
        "https://maps.google.com/maps?q=Applewood",
        "https://jrhof.org/wp-content/uploads/2026/03/golf_tournament_flyer_2026-1-2-2-pdf.jpg",
        "https://jrhof.org/wp-content/uploads/2026/03/golf_tournament_flyer_2026-1-2-2.pdf",
        "https://jrhof.org/wp-content/uploads/2026/03/2026-Golf-Tournament-Raffle-Tickets.jpg",
        "https://buy.stripe.com/7sYdR84L01mG0F64wO93y02",
        "https://jrhof.org/wp-content/uploads/2026/03/2026-Golf-Tournament-Mulligan.jpg",
        "https://buy.stripe.com/5kQ3cuelA6H04VmbZg93y03",
        "https://donate.stripe.com/00w5kC7Xc4yS1Jagfw93y01"
      ],
      "mediaRefs": [
        "https://jrhof.org/wp-content/uploads/2026/03/golf_tournament_flyer_2026-1-2-2-pdf.jpg",
        "https://jrhof.org/wp-content/uploads/2026/03/golf_tournament_flyer_2026-1-2-2.pdf",
        "https://jrhof.org/wp-content/uploads/2026/03/2026-Golf-Tournament-Raffle-Tickets.jpg",
        "https://jrhof.org/wp-content/uploads/2026/03/2026-Golf-Tournament-Mulligan.jpg"
      ],
      "galleryIds": [],
      "galleryAttachmentIds": [],
      "eventbriteLinks": [
        "https://www.eventbrite.com/e/joe-rossi-hof-golf-tournament-2026-tickets-1985644019715"
      ],
      "stripeLinks": [
        "https://buy.stripe.com/7sYdR84L01mG0F64wO93y02",
        "https://buy.stripe.com/5kQ3cuelA6H04VmbZg93y03",
        "https://donate.stripe.com/00w5kC7Xc4yS1Jagfw93y01"
      ],
      "suggestedCanonicalUrl": "/events/2026/golf-tournament/",
      "registrationMigrationStatus": "native-form-required",
      "registrationFieldsFoundOrImplied": [
        {
          "field": "contactName",
          "basis": "implied-by-registration"
        },
        {
          "field": "contactEmail",
          "basis": "existing-repo-form"
        },
        {
          "field": "contactPhone",
          "basis": "implied-by-event-operations"
        },
        {
          "field": "golferQuantity",
          "basis": "wordpress-per-golfer-pricing-and-existing-repo-form"
        },
        {
          "field": "golferNames",
          "basis": "existing-repo-form"
        },
        {
          "field": "golferEmails",
          "basis": "existing-repo-form"
        },
        {
          "field": "teamOrFoursomeRequest",
          "basis": "existing-repo-form"
        },
        {
          "field": "raffleTicketQuantity",
          "basis": "wordpress-add-on-and-existing-repo-form"
        },
        {
          "field": "mulliganQuantity",
          "basis": "wordpress-add-on"
        },
        {
          "field": "commentsOrAccessibilityNeeds",
          "basis": "existing-repo-comments-plus-implied"
        }
      ]
    },
    {
      "wordpressId": 785,
      "status": "publish",
      "title": "2026 Colorado Baseball Umpires Joe Rossi Hall of Fame Induction Banquet",
      "slug": "2026-hof-induction-banquet",
      "url": "https://jrhof.org/2026-hof-induction-banquet/",
      "eventType": "hof-banquet",
      "year": 2026,
      "publishedAt": "2025-11-15 17:01:25",
      "modifiedAt": "2026-01-27 03:47:11",
      "categories": [
        {
          "domain": "category",
          "nicename": "banquet",
          "label": "Banquet"
        }
      ],
      "contentText": "2026 Colorado Baseball Umpires Joe Rossi Hall of Fame Induction Banquet Days Hours Minutes Seconds Check back soon for photos of this special event. It is time again for one of the highlights of the high school baseball season — the 2026 annual Colorado Baseball Umpires Joe Rossi Hall of Fame Induction Banquet. This special event is held the day before the CHSBUA Master Clinic and honors the exceptional individuals who have contributed so much to the game of baseball in Colorado. Please give serious consideration to attending this banquet to celebrate and show gratitude to our new inductees. Terry Angell George Demetriou Fred Zuercher Don’t forget to include your significant others and friends in your registration! Register Now Event Details Date : Saturday, January 31, 2026 Time : 31, 2026 Location: Holiday Inn Denver–Lakewood 7390 W. Hampden Ave., Lakewood, CO 80227 Hotel Accommodations A special room rate is available at the Holiday Inn Denver–Lakewood. Make your reservation by calling (303) 980-9200 and using GROUP CODE: JRH before January 16, 2026 . Registration $43 before December 14, 2025 $50 from December 15, 2025 to January 25, 2026 Business casual attire is recommended. Please include significant others and friends in your registration. Register Now Share Blocksy: Share Box",
      "wordCount": 205,
      "links": [
        "https://jrhof.org/wp-content/uploads/2026/01/Terry_Angell.webp",
        "https://jrhof.org/inductees/terry_angell/",
        "https://jrhof.org/wp-content/uploads/2026/01/George_Demetriou.webp",
        "https://jrhof.org/inductees/george_demetriou/",
        "https://jrhof.org/wp-content/uploads/2026/01/Fred_Zuercher.webp",
        "https://jrhof.org/inductees/fred_zuercher/",
        "https://www.eventbrite.com/e/chsbua-joe-rossi-2026-hof-banquet-tickets-1948078227419?aff=oddtdtcreator",
        "http://www.w3.org/2000/svg",
        "https://maps.google.com/maps?q=7390",
        "https://jrhof.org/wp-content/uploads/2025/11/events_hof-banquet_2026_JR-HOF-Registration-2026.png",
        "https://cdn.jrhof.org/events/hof-banquet/2026/JR%20HOF%20Registration%202026.pdf"
      ],
      "mediaRefs": [
        "https://jrhof.org/wp-content/uploads/2026/01/Terry_Angell.webp",
        "https://jrhof.org/wp-content/uploads/2026/01/George_Demetriou.webp",
        "https://jrhof.org/wp-content/uploads/2026/01/Fred_Zuercher.webp",
        "https://jrhof.org/wp-content/uploads/2025/11/events_hof-banquet_2026_JR-HOF-Registration-2026.png"
      ],
      "galleryIds": [],
      "galleryAttachmentIds": [],
      "eventbriteLinks": [
        "https://www.eventbrite.com/e/chsbua-joe-rossi-2026-hof-banquet-tickets-1948078227419?aff=oddtdtcreator"
      ],
      "stripeLinks": [],
      "suggestedCanonicalUrl": "/events/2026/hof-banquet/",
      "registrationMigrationStatus": "native-form-required",
      "registrationFieldsFoundOrImplied": [
        {
          "field": "contactName",
          "basis": "implied-by-registration"
        },
        {
          "field": "contactEmail",
          "basis": "implied-by-confirmation"
        },
        {
          "field": "contactPhone",
          "basis": "implied-by-event-operations"
        },
        {
          "field": "ticketQuantity",
          "basis": "wordpress-tiered-per-attendee-pricing"
        },
        {
          "field": "attendeeNames",
          "basis": "wordpress-significant-others-and-friends-language"
        },
        {
          "field": "seatingOrGroupRequest",
          "basis": "implied-by-banquet-format"
        },
        {
          "field": "dietaryOrAccessibilityNeeds",
          "basis": "implied-by-banquet-format-not-explicitly-present"
        }
      ]
    },
    {
      "wordpressId": 1488,
      "status": "publish",
      "title": "2025 Joe Rossi Hall of Fame Presents - The Umpire's Cup III",
      "slug": "2025-joe-rossi-hall-of-fame-presents-the-umpires-cup-iii",
      "url": "https://jrhof.org/2025-joe-rossi-hall-of-fame-presents-the-umpires-cup-iii/",
      "eventType": "golf-tournament",
      "year": 2025,
      "publishedAt": "2025-06-21 21:13:00",
      "modifiedAt": "2026-01-27 03:50:42",
      "categories": [
        {
          "domain": "category",
          "nicename": "golf",
          "label": "Golf"
        }
      ],
      "contentText": "2025 Joe Rossi Hall of Fame Presents - The Umpire's Cup III Sponsored by: KSK | Photography by: LeBaron Portraits Welcome to the gallery for The 2025 Umpire's Cup III Golf Tournament! Here you can relive the highlights and memorable moments from this year's Golf Tournament Fundraising event. Special thanks to Scott LeBaron and LeBaron Portraits for capturing these amazing images.",
      "wordCount": 59,
      "links": [
        "https://www.lebaronportraits.com/"
      ],
      "mediaRefs": [],
      "galleryIds": [
        3520
      ],
      "galleryAttachmentIds": [
        3521,
        3522,
        3523,
        3524,
        3525,
        3526,
        3527,
        3528,
        3529,
        3530,
        3531,
        3532,
        3533,
        3534,
        3535,
        3536,
        3537,
        3538,
        3539,
        3540,
        3541,
        3542,
        3543,
        3544,
        3545,
        3546,
        3547,
        3548,
        3549,
        3550,
        3551,
        3552,
        3553,
        3554,
        3555,
        3556,
        3557,
        3558,
        3559,
        3560,
        3561,
        3562,
        3563,
        3564,
        3565,
        3566,
        3567,
        3568,
        3569,
        3570,
        3571,
        3572,
        3573,
        3574,
        3575,
        3576,
        3577,
        3578,
        3579,
        3580,
        3581,
        3582,
        3583,
        3584,
        3585,
        3586,
        3587,
        3588,
        3589,
        3590,
        3591,
        3592,
        3593,
        3594,
        3595,
        3596,
        3597,
        3598,
        3599,
        3600,
        3601,
        3602,
        3603,
        3604,
        3605,
        3606,
        3607,
        3608,
        3609,
        3610,
        3611,
        3612,
        3613,
        3614,
        3615,
        3616,
        3617,
        3618,
        3619,
        3620,
        3621,
        3622,
        3624,
        3625,
        3626,
        3627,
        3628,
        3629,
        3630,
        3631,
        3632,
        3633,
        3634,
        3635,
        3636,
        3637,
        3638,
        3639,
        3640,
        3641,
        3642,
        3643,
        3644,
        3645,
        3646,
        3647,
        3648,
        3649,
        3650,
        3651,
        3652,
        3653,
        3654,
        3655,
        3656,
        3657,
        3659,
        3660,
        3661,
        3662,
        3663,
        3664,
        3665,
        3666,
        3667,
        3668,
        3669,
        3670,
        3671,
        3672,
        3673,
        3674,
        3675,
        3676,
        3677,
        3678,
        3679,
        3680,
        3681,
        3682,
        3683,
        3684,
        3685,
        3686,
        3687,
        3688,
        3689,
        3690,
        3691,
        3692,
        3693,
        3694,
        3695,
        3696,
        3697,
        3698,
        3699,
        3700,
        3701,
        3702,
        3703,
        3704,
        3705,
        3706,
        3707,
        3708,
        3709,
        3710,
        3711,
        3712,
        3713,
        3714,
        3715,
        3716,
        3718,
        3719,
        3720,
        3721,
        3722,
        3723,
        3724,
        3725,
        3726,
        3727,
        3728,
        3729,
        3730,
        3731,
        3732,
        3733,
        3734,
        3735,
        3736,
        3737,
        3738,
        3739,
        3740,
        3741,
        3742,
        3743,
        3744,
        3745,
        3746,
        3747,
        3748,
        3749,
        3750,
        3751,
        3752,
        3753,
        3754,
        3755,
        3756,
        3757,
        3758,
        3759,
        3760,
        3761,
        3762,
        3763,
        3764,
        3765,
        3766,
        3767
      ],
      "eventbriteLinks": [],
      "stripeLinks": [],
      "suggestedCanonicalUrl": "/events/2025/golf-tournament/",
      "registrationMigrationStatus": "native-form-required",
      "registrationFieldsFoundOrImplied": []
    },
    {
      "wordpressId": 1241,
      "status": "publish",
      "title": "2024 Joe Rossi Hall of Fame Presents - The Umpire's Cup II",
      "slug": "2024-joe-rossi-hall-of-fame-presents-the-umpires-cup-ii",
      "url": "https://jrhof.org/2024-joe-rossi-hall-of-fame-presents-the-umpires-cup-ii/",
      "eventType": "golf-tournament",
      "year": 2024,
      "publishedAt": "2024-06-22 18:34:00",
      "modifiedAt": "2026-01-27 03:36:55",
      "categories": [
        {
          "domain": "category",
          "nicename": "golf",
          "label": "Golf"
        }
      ],
      "contentText": "2024 Joe Rossi Hall of Fame Presents - The Umpire's Cup II Sponsored by: KSK | Photography by: LeBaron Portraits Welcome to the gallery for The 2024 Umpire's Cup II Golf Tournament! Here you can relive the highlights and memorable moments from this year's golf tournament fundraising event. Special thanks to Scott LeBaron and LeBaron Portraits for capturing these amazing images.",
      "wordCount": 59,
      "links": [
        "https://www.lebaronportraits.com/"
      ],
      "mediaRefs": [],
      "galleryIds": [
        3360
      ],
      "galleryAttachmentIds": [
        3361,
        3362,
        3363,
        3364,
        3365,
        3366,
        3367,
        3368,
        3369,
        3370,
        3371,
        3372,
        3373,
        3374,
        3375,
        3376,
        3377,
        3378,
        3379,
        3380,
        3381,
        3382,
        3383,
        3384,
        3385,
        3386,
        3387,
        3388,
        3389,
        3390,
        3391,
        3392,
        3393,
        3394,
        3395,
        3396,
        3397,
        3398,
        3399,
        3400,
        3401,
        3402,
        3403,
        3404,
        3405,
        3406,
        3407,
        3408,
        3409,
        3410,
        3411,
        3412,
        3413,
        3414,
        3415,
        3416,
        3417,
        3418,
        3419,
        3420,
        3421,
        3422,
        3423,
        3424,
        3425,
        3426,
        3427,
        3428,
        3429,
        3430,
        3431,
        3432,
        3433,
        3434,
        3435,
        3436,
        3437,
        3438,
        3439,
        3440,
        3441,
        3442,
        3443,
        3444,
        3445,
        3446,
        3447,
        3448,
        3449,
        3450,
        3451,
        3452,
        3453,
        3454,
        3455,
        3456,
        3457,
        3458,
        3459,
        3460,
        3461,
        3462,
        3463,
        3464,
        3465,
        3466,
        3467,
        3468,
        3469,
        3470,
        3471,
        3472,
        3473,
        3474,
        3475,
        3476,
        3477,
        3478,
        3479,
        3480,
        3481,
        3482,
        3483,
        3484,
        3485,
        3486,
        3487,
        3488,
        3489,
        3490,
        3491,
        3492,
        3493,
        3494,
        3495,
        3496,
        3497,
        3498,
        3499,
        3500,
        3501,
        3502,
        3503,
        3504,
        3505,
        3506,
        3507,
        3508,
        3509,
        3510,
        3511,
        3512,
        3513,
        3514,
        3515,
        3516,
        3517,
        3518
      ],
      "eventbriteLinks": [],
      "stripeLinks": [],
      "suggestedCanonicalUrl": "/events/2024/golf-tournament/",
      "registrationMigrationStatus": "native-form-required",
      "registrationFieldsFoundOrImplied": []
    }
  ]
}
